pyqcas/__init__.py
pyqcas/bit_array_cell.py
pyqcas/data_transfer.py
pyqcas/eqasm.py
pyqcas/eqasm_lexer.py
pyqcas/eqasm_parser.py
pyqcas/fpr.py
pyqcas/global_config.py
pyqcas/gpr.py
pyqcas/insn.py
pyqcas/memory.py
pyqcas/qcp.py
pyqcas/qotr.py
pyqcas/quantum_coprocessor.py
pyqcas/utils.py
pyqcas/qubit_state_sim/__init__.py
pyqcas/qubit_state_sim/if_qubit_sim.py
pyqcas/qubit_state_sim/quantumsim.py
pyqcas-0.1.0b0.dist-info/LICENSE
pyqcas-0.1.0b0.dist-info/METADATA
pyqcas-0.1.0b0.dist-info/WHEEL
pyqcas-0.1.0b0.dist-info/top_level.txt
pyqcas-0.1.0b0.dist-info/RECORD
