Metadata-Version: 2.1
Name: pyqcas
Version: 0.1.0b0
Summary: A functional eQASM simulator without timing modeling
Home-page: https://gitee.com/hpcl_quanta/pyqcas
Author: Xiang Fu
Author-email: gtaifu@gmail.com
License: UNKNOWN
Project-URL: Bug Tracker, https://gitee.com/hpcl_quanta/pyqcas/issues
Platform: UNKNOWN
Classifier: Programming Language :: Python :: 3 :: Only
Classifier: License :: OSI Approved :: Apache Software License
Classifier: Operating System :: OS Independent
Requires-Python: >=3.7
License-File: LICENSE
Requires-Dist: quantumsim (==0.2.0)
Requires-Dist: bitstring
Requires-Dist: ply
